{".class": "MypyFile", "_fullname": "sqlalchemy.dialects.postgresql.ext", "future_import_flags": [], "is_partial_stub_package": false, "is_stub": true, "names": {".class": "SymbolTable", "Any": {".class": "SymbolTableNode", "cross_ref": "typing.Any", "kind": "Gdef", "module_hidden": true, "module_public": false}, "ColumnCollectionConstraint": {".class": "SymbolTableNode", "cross_ref": "sqlalchemy.sql.schema.ColumnCollectionConstraint", "kind": "Gdef", "module_hidden": true, "module_public": false}, "ExcludeConstraint": {".class": "SymbolTableNode", "kind": "Gdef", "node": {".class": "TypeInfo", "_promote": [], "abstract_attributes": [], "bases": ["sqlalchemy.sql.schema.ColumnCollectionConstraint"], "declared_metaclass": null, "defn": {".class": "ClassDef", "fullname": "sqlalchemy.dialects.postgresql.ext.ExcludeConstraint", "name": "ExcludeConstraint", "type_vars": []}, "deletable_attributes": [], "flags": [], "fullname": "sqlalchemy.dialects.postgresql.ext.ExcludeConstraint", "has_param_spec_type": false, "metaclass_type": null, "metadata": {}, "module_name": "sqlalchemy.dialects.postgresql.ext", "mro": ["sqlalchemy.dialects.postgresql.ext.ExcludeConstraint", "sqlalchemy.sql.schema.ColumnCollectionConstraint", "sqlalchemy.sql.schema.ColumnCollectionMixin", "sqlalchemy.sql.schema.Constraint", "sqlalchemy.sql.base.DialectKWArgs", "sqlalchemy.sql.schema.SchemaItem", "sqlalchemy.sql.base.SchemaEventTarget", "sqlalchemy.sql.visitors.Traversible", "builtins.object"], "names": {".class": "SymbolTable", "__init__": {".class": "SymbolTableNode", "kind": "Mdef", "node": {".class": "FuncDef", "abstract_status": 0, "arg_kinds": [0, 2, 4], "arg_names": ["self", "elements", "kw"], "flags": [], "fullname": "sqlalchemy.dialects.postgresql.ext.ExcludeConstraint.__init__", "name": "__init__", "type": {".class": "CallableType", "arg_kinds": [0, 2, 4], "arg_names": ["self", "elements", "kw"], "arg_types": ["sqlalchemy.dialects.postgresql.ext.ExcludeConstraint", {".class": "AnyType", "missing_import_name": null, "source_any": null, "type_of_any": 1}, {".class": "AnyType", "missing_import_name": null, "source_any": null, "type_of_any": 1}], "bound_args": [], "def_extras": {"first_arg": "self"}, "fallback": "builtins.function", "from_concatenate": false, "implicit": false, "is_ellipsis_args": false, "name": "__init__ of ExcludeConstraint", "ret_type": {".class": "NoneType"}, "type_guard": null, "unpack_kwargs": false, "variables": []}}}, "__visit_name__": {".class": "SymbolTableNode", "kind": "Mdef", "node": {".class": "Var", "flags": ["is_initialized_in_class", "is_ready"], "fullname": "sqlalchemy.dialects.postgresql.ext.ExcludeConstraint.__visit_name__", "name": "__visit_name__", "type": "builtins.str"}}, "create_drop_stringify_dialect": {".class": "SymbolTableNode", "kind": "Mdef", "node": {".class": "Var", "flags": ["is_initialized_in_class", "is_ready"], "fullname": "sqlalchemy.dialects.postgresql.ext.ExcludeConstraint.create_drop_stringify_dialect", "name": "create_drop_stringify_dialect", "type": "builtins.str"}}, "inherit_cache": {".class": "SymbolTableNode", "kind": "Mdef", "node": {".class": "Var", "flags": ["is_initialized_in_class", "is_ready"], "fullname": "sqlalchemy.dialects.postgresql.ext.ExcludeConstraint.inherit_cache", "name": "inherit_cache", "type": "builtins.bool"}}, "operators": {".class": "SymbolTableNode", "kind": "Mdef", "node": {".class": "Var", "flags": ["is_initialized_in_class", "is_ready"], "fullname": "sqlalchemy.dialects.postgresql.ext.ExcludeConstraint.operators", "name": "operators", "type": {".class": "AnyType", "missing_import_name": null, "source_any": null, "type_of_any": 2}}}, "ops": {".class": "SymbolTableNode", "kind": "Mdef", "node": {".class": "Var", "flags": ["is_initialized_in_class", "is_ready"], "fullname": "sqlalchemy.dialects.postgresql.ext.ExcludeConstraint.ops", "name": "ops", "type": {".class": "AnyType", "missing_import_name": null, "source_any": null, "type_of_any": 2}}}, "using": {".class": "SymbolTableNode", "kind": "Mdef", "node": {".class": "Var", "flags": ["is_initialized_in_class", "is_ready"], "fullname": "sqlalchemy.dialects.postgresql.ext.ExcludeConstraint.using", "name": "using", "type": {".class": "AnyType", "missing_import_name": null, "source_any": null, "type_of_any": 2}}}, "where": {".class": "SymbolTableNode", "kind": "Mdef", "node": {".class": "Var", "flags": ["is_initialized_in_class", "is_ready"], "fullname": "sqlalchemy.dialects.postgresql.ext.ExcludeConstraint.where", "name": "where", "type": {".class": "AnyType", "missing_import_name": null, "source_any": null, "type_of_any": 2}}}}, "self_type": null, "slots": null, "tuple_type": null, "type_vars": [], "typeddict_type": null}}, "__annotations__": {".class": "SymbolTableNode", "kind": "Gdef", "node": {".class": "Var", "flags": ["is_ready"], "fullname": "sqlalchemy.dialects.postgresql.ext.__annotations__", "name": "__annotations__", "type": {".class": "Instance", "args": ["builtins.str", {".class": "AnyType", "missing_import_name": null, "source_any": null, "type_of_any": 6}], "type_ref": "builtins.dict"}}}, "__doc__": {".class": "SymbolTableNode", "kind": "Gdef", "node": {".class": "Var", "flags": ["is_ready"], "fullname": "sqlalchemy.dialects.postgresql.ext.__doc__", "name": "__doc__", "type": "builtins.str"}}, "__file__": {".class": "SymbolTableNode", "kind": "Gdef", "node": {".class": "Var", "flags": ["is_ready"], "fullname": "sqlalchemy.dialects.postgresql.ext.__file__", "name": "__file__", "type": "builtins.str"}}, "__name__": {".class": "SymbolTableNode", "kind": "Gdef", "node": {".class": "Var", "flags": ["is_ready"], "fullname": "sqlalchemy.dialects.postgresql.ext.__name__", "name": "__name__", "type": "builtins.str"}}, "__package__": {".class": "SymbolTableNode", "kind": "Gdef", "node": {".class": "Var", "flags": ["is_ready"], "fullname": "sqlalchemy.dialects.postgresql.ext.__package__", "name": "__package__", "type": "builtins.str"}}, "aggregate_order_by": {".class": "SymbolTableNode", "kind": "Gdef", "node": {".class": "TypeInfo", "_promote": [], "abstract_attributes": [], "bases": [{".class": "Instance", "args": [{".class": "AnyType", "missing_import_name": null, "source_any": null, "type_of_any": 2}], "type_ref": "sqlalchemy.sql.elements.ColumnElement"}], "declared_metaclass": null, "defn": {".class": "ClassDef", "fullname": "sqlalchemy.dialects.postgresql.ext.aggregate_order_by", "name": "aggregate_order_by", "type_vars": []}, "deletable_attributes": [], "flags": [], "fullname": "sqlalchemy.dialects.postgresql.ext.aggregate_order_by", "has_param_spec_type": false, "metaclass_type": null, "metadata": {}, "module_name": "sqlalchemy.dialects.postgresql.ext", "mro": ["sqlalchemy.dialects.postgresql.ext.aggregate_order_by", "sqlalchemy.sql.elements.ColumnElement", "sqlalchemy.sql.roles.ColumnArgumentOrKeyRole", "sqlalchemy.sql.roles.ColumnArgumentRole", "sqlalchemy.sql.roles.StatementOptionRole", "sqlalchemy.sql.roles.WhereHavingRole", "sqlalchemy.sql.roles.OnClauseRole", "sqlalchemy.sql.roles.BinaryElementRole", "sqlalchemy.sql.roles.ExpressionElementRole", "sqlalchemy.sql.roles.OrderByRole", "sqlalchemy.sql.roles.ColumnsClauseRole", "sqlalchemy.sql.roles.AllowsLambdaRole", "sqlalchemy.sql.roles.ByOfRole", "sqlalchemy.sql.roles.UsesInspection", "sqlalchemy.sql.roles.ColumnListRole", "sqlalchemy.sql.roles.LimitOffsetRole", "sqlalchemy.sql.roles.DMLColumnRole", "sqlalchemy.sql.roles.DDLConstraintColumnRole", "sqlalchemy.sql.roles.DDLExpressionRole", "sqlalchemy.sql.roles.StructuralRole", "sqlalchemy.sql.operators.ColumnOperators", "sqlalchemy.sql.operators.Operators", "sqlalchemy.sql.elements.ClauseElement", "sqlalchemy.sql.roles.SQLRole", "sqlalchemy.sql.annotation.SupportsWrappingAnnotations", "sqlalchemy.sql.annotation.SupportsAnnotations", "sqlalchemy.sql.traversals.MemoizedHasCacheKey", "sqlalchemy.sql.traversals.HasCacheKey", "sqlalchemy.util.langhelpers.HasMemoized", "sqlalchemy.sql.traversals.HasCopyInternals", "sqlalchemy.sql.visitors.Traversible", "builtins.object"], "names": {".class": "SymbolTable", "__init__": {".class": "SymbolTableNode", "kind": "Mdef", "node": {".class": "FuncDef", "abstract_status": 0, "arg_kinds": [0, 0, 2], "arg_names": ["self", "target", "order_by"], "flags": [], "fullname": "sqlalchemy.dialects.postgresql.ext.aggregate_order_by.__init__", "name": "__init__", "type": {".class": "CallableType", "arg_kinds": [0, 0, 2], "arg_names": ["self", "target", "order_by"], "arg_types": ["sqlalchemy.dialects.postgresql.ext.aggregate_order_by", {".class": "AnyType", "missing_import_name": null, "source_any": null, "type_of_any": 1}, {".class": "AnyType", "missing_import_name": null, "source_any": null, "type_of_any": 1}], "bound_args": [], "def_extras": {"first_arg": "self"}, "fallback": "builtins.function", "from_concatenate": false, "implicit": false, "is_ellipsis_args": false, "name": "__init__ of aggregate_order_by", "ret_type": {".class": "NoneType"}, "type_guard": null, "unpack_kwargs": false, "variables": []}}}, "__visit_name__": {".class": "SymbolTableNode", "kind": "Mdef", "node": {".class": "Var", "flags": ["is_initialized_in_class", "is_ready"], "fullname": "sqlalchemy.dialects.postgresql.ext.aggregate_order_by.__visit_name__", "name": "__visit_name__", "type": "builtins.str"}}, "get_children": {".class": "SymbolTableNode", "kind": "Mdef", "node": {".class": "FuncDef", "abstract_status": 0, "arg_kinds": [0, 4], "arg_names": ["self", "kwargs"], "flags": [], "fullname": "sqlalchemy.dialects.postgresql.ext.aggregate_order_by.get_children", "name": "get_children", "type": null}}, "order_by": {".class": "SymbolTableNode", "kind": "Mdef", "node": {".class": "Var", "flags": ["is_initialized_in_class", "is_ready"], "fullname": "sqlalchemy.dialects.postgresql.ext.aggregate_order_by.order_by", "name": "order_by", "type": {".class": "AnyType", "missing_import_name": null, "source_any": null, "type_of_any": 2}}}, "self_group": {".class": "SymbolTableNode", "kind": "Mdef", "node": {".class": "FuncDef", "abstract_status": 0, "arg_kinds": [0, 1], "arg_names": ["self", "against"], "flags": [], "fullname": "sqlalchemy.dialects.postgresql.ext.aggregate_order_by.self_group", "name": "self_group", "type": {".class": "CallableType", "arg_kinds": [0, 1], "arg_names": ["self", "against"], "arg_types": ["sqlalchemy.dialects.postgresql.ext.aggregate_order_by", {".class": "UnionType", "items": [{".class": "AnyType", "missing_import_name": null, "source_any": null, "type_of_any": 2}, {".class": "NoneType"}]}], "bound_args": [], "def_extras": {"first_arg": "self"}, "fallback": "builtins.function", "from_concatenate": false, "implicit": false, "is_ellipsis_args": false, "name": "self_group of aggregate_order_by", "ret_type": {".class": "AnyType", "missing_import_name": null, "source_any": null, "type_of_any": 1}, "type_guard": null, "unpack_kwargs": false, "variables": []}}}, "stringify_dialect": {".class": "SymbolTableNode", "kind": "Mdef", "node": {".class": "Var", "flags": ["is_initialized_in_class", "is_ready"], "fullname": "sqlalchemy.dialects.postgresql.ext.aggregate_order_by.stringify_dialect", "name": "stringify_dialect", "type": "builtins.str"}}, "target": {".class": "SymbolTableNode", "kind": "Mdef", "node": {".class": "Var", "flags": ["is_initialized_in_class", "is_ready"], "fullname": "sqlalchemy.dialects.postgresql.ext.aggregate_order_by.target", "name": "target", "type": {".class": "AnyType", "missing_import_name": null, "source_any": null, "type_of_any": 2}}}, "type": {".class": "SymbolTableNode", "kind": "Mdef", "node": {".class": "Var", "flags": ["is_initialized_in_class", "is_ready"], "fullname": "sqlalchemy.dialects.postgresql.ext.aggregate_order_by.type", "name": "type", "type": {".class": "AnyType", "missing_import_name": null, "source_any": null, "type_of_any": 2}}}}, "self_type": null, "slots": null, "tuple_type": null, "type_vars": [], "typeddict_type": null}}, "array_agg": {".class": "SymbolTableNode", "kind": "Gdef", "node": {".class": "FuncDef", "abstract_status": 0, "arg_kinds": [2, 4], "arg_names": ["arg", "kw"], "flags": [], "fullname": "sqlalchemy.dialects.postgresql.ext.array_agg", "name": "array_agg", "type": null}}, "expression": {".class": "SymbolTableNode", "cross_ref": "sqlalchemy.sql.expression", "kind": "Gdef", "module_hidden": true, "module_public": false}}, "path": "/usr/lib/python3/dist-packages/sqlalchemy-stubs/dialects/postgresql/ext.pyi"}